Metadata-Version: 2.1
Name: py-monadic-error-handling
Version: 1.1.1
Summary: Monadic error handling implementation for python functions.
Author: João Vitor Ceolin Prudente
